thonnycontrib/backend/py5_imported_mode_backend.py
thonnycontrib/kyanite_theme_syntax/__init__.py
thonnycontrib/kyanite_theme_ui/__init__.py
thonnycontrib/thonny-py5mode/__init__.py
thonnycontrib/thonny-py5mode/_version.py
thonnycontrib/thonny-py5mode/about_plugin.py
thonnycontrib/thonny-py5mode/install_jdk.py
thonnycontrib/thonny-py5mode/py5colorpicker/tkcolorpicker/__init__.py
thonnycontrib/thonny-py5mode/py5colorpicker/tkcolorpicker/__main__.py
thonnycontrib/thonny-py5mode/py5colorpicker/tkcolorpicker/alphabar.py
thonnycontrib/thonny-py5mode/py5colorpicker/tkcolorpicker/colorpicker.py
thonnycontrib/thonny-py5mode/py5colorpicker/tkcolorpicker/colorsquare.py
thonnycontrib/thonny-py5mode/py5colorpicker/tkcolorpicker/functions.py
thonnycontrib/thonny-py5mode/py5colorpicker/tkcolorpicker/gradientbar.py
thonnycontrib/thonny-py5mode/py5colorpicker/tkcolorpicker/limitvar.py
thonnycontrib/thonny-py5mode/py5colorpicker/tkcolorpicker/spinbox.py
thonny_py5mode-0.4.7a0.dist-info/LICENSE
thonny_py5mode-0.4.7a0.dist-info/METADATA
thonny_py5mode-0.4.7a0.dist-info/WHEEL
thonny_py5mode-0.4.7a0.dist-info/top_level.txt
thonny_py5mode-0.4.7a0.dist-info/RECORD
