Metadata-Version: 2.1
Name: thonny-py5mode
Version: 0.4.7a0
Summary: py5 mode plugin for Thonny
Home-page: https://github.com/tabreturn/thonny-py5mode
Author: tabreturn
Author-email: thonny-py5mode@tabreturn.com
License: WTFPL
Classifier: Environment :: Plugins
Classifier: Topic :: Multimedia :: Graphics
Classifier: Topic :: Text Editors :: Integrated Development Environments (IDE)
License-File: LICENSE
Requires-Dist: install-jdk ==1.1.0
Requires-Dist: py5
Requires-Dist: pyperclip ==1.9.0
